gitlist/__init__.py
gitlist/gitlist.py
gitlist-0.1.1.dist-info/COPYING
gitlist-0.1.1.dist-info/METADATA
gitlist-0.1.1.dist-info/WHEEL
gitlist-0.1.1.dist-info/entry_points.txt
gitlist-0.1.1.dist-info/top_level.txt
gitlist-0.1.1.dist-info/RECORD
