Metadata-Version: 2.1
Name: gitlist
Version: 0.1.1
Summary: Displays the state of your local Git repositories.
Home-page: https://github.com/craigiansmith/gitlist
Author: Craig Smith
Author-email: hello@craigiansmith.com.au
License: GPLv3+
Project-URL: Source, https://github.com/craigiansmith/gitlist
Keywords: git development source status
Platform: UNKNOWN
Classifier: Development Status :: 1 - Planning
Classifier: Intended Audience :: Developers
Classifier: Topic :: Software Development :: Version Control :: Git
Classifier: License :: OSI Approved :: GNU General Public License v3 or later (GPLv3+)
Classifier: Programming Language :: Python :: 3.8
Requires-Python: >=3.3
